{
  "levels": [
    {
      "level": 1,
      "price": "0",
      "links": 0,
      "display_item": {
        "type": "TRAPPED_CHEST",
        "name": "&b&lLinks",
        "custom_model_data": -1,
        "glow": false,
        "lore": [
          "&7",
          "Current Level: &a&l%level%&7",
          "Next Level: &a&l%nextLevel%&7",
          "Next Level Price: &a&l%nextLevelPrice%&7",
          "&7",
          "Links: &a&l%links%&7",
          "&7"
        ]
      }
    },
    {
      "level": 2,
      "price": "150.00",
      "links": 2,
      "display_item": {
        "type": "CHEST",
        "name": "&b&lLinks",
        "custom_model_data": -1,
        "glow": false,
        "lore": [
          "&7",
          "Current Level: &a&l%level%&7",
          "Next Level: &a&l%nextLevel%&7",
          "Next Level Price: &a&l%nextLevelPrice%&7",
          "&7",
          "Links: &a&l%links%&7",
          "&7"
        ]
      }
    },
    {
      "level": 3,
      "price": "300.00",
      "links": 3,
      "display_item": {
        "type": "ENDER_CHEST",
        "name": "&b&lLinks",
        "custom_model_data": -1,
        "glow": false,
        "lore": [
          "&7",
          "Current Level: &a&l%level%&7",
          "Next Level: &a&l%nextLevel%&7",
          "Next Level Price: &a&l%nextLevelPrice%&7",
          "&7",
          "Links: &a&l%links%&7",
          "&7"
        ]
      }
    }
  ],
  "voidchest_types": [
    "default",
    "default2"
  ]
}
